hnhm/__init__.py
hnhm/cli.py
hnhm/core/__init__.py
hnhm/core/attribute.py
hnhm/core/entity.py
hnhm/core/error.py
hnhm/core/group.py
hnhm/core/layout.py
hnhm/core/link.py
hnhm/core/migration.py
hnhm/core/priority.py
hnhm/core/sql.py
hnhm/core/state.py
hnhm/core/task.py
hnhm/file_state.py
hnhm/flow.py
hnhm/hnhm.py
hnhm/hnhm_attribute.py
hnhm/hnhm_entity.py
hnhm/hnhm_link.py
hnhm/hnhm_registry.py
hnhm/plan_printer.py
hnhm/postgres/__init__.py
hnhm/postgres/sql.py
hnhm/postgres/sql_templates/create_attribute.sql
hnhm/postgres/sql_templates/create_group.sql
hnhm/postgres/sql_templates/create_hub.sql
hnhm/postgres/sql_templates/create_link.sql
hnhm/postgres/sql_templates/create_stage.sql
hnhm/postgres/sql_templates/load_hub.sql
hnhm/postgres/sql_templates/load_ignore.sql
hnhm/postgres/sql_templates/load_link.sql
hnhm/postgres/sql_templates/load_new.sql
hnhm/postgres/sql_templates/load_update.sql
hnhm/postgres/sql_templates/update_entity_view.sql
hnhm-0.0.11.dist-info/METADATA
hnhm-0.0.11.dist-info/WHEEL
hnhm-0.0.11.dist-info/entry_points.txt
hnhm-0.0.11.dist-info/RECORD
