Metadata-Version: 2.1
Name: hnhm
Version: 0.0.11
Summary: hNhM – highly Normalized hybrid Model.
Home-page: https://marchinho11.github.io/hnhm
Keywords: hnhm,datavault,anchormodeling,python
Author: Arseny Egorov
Author-email: egoroff-ars@yandex.ru
Maintainer: Arseny Egorov
Maintainer-email: egoroff-ars@yandex.ru
Requires-Python: >=3.10,<3.11
Classifier: Programming Language :: Python :: 3
Classifier: Programming Language :: Python :: 3.10
Requires-Dist: Jinja2 (>=3.1,<3.2)
Requires-Dist: click (>=8.1,<8.2)
Requires-Dist: psycopg[binary] (>=3.1,<3.2)
Requires-Dist: pydantic (>=2.6,<2.7)
Project-URL: Documentation, https://marchinho11.github.io/hnhm
Project-URL: Repository, https://github.com/marchinho11/hnhm
